hepdata_converter_ws_client/__init__.py
hepdata_converter_ws_client/version.py
hepdata_converter_ws_client-0.2.2.dist-info/LICENSE.txt
hepdata_converter_ws_client-0.2.2.dist-info/METADATA
hepdata_converter_ws_client-0.2.2.dist-info/WHEEL
hepdata_converter_ws_client-0.2.2.dist-info/top_level.txt
hepdata_converter_ws_client-0.2.2.dist-info/RECORD
