Metadata-Version: 2.1
Name: hepdata-converter-ws-client
Version: 0.2.2
Summary: Simple wrapper for requests, to ease use of HEPData Converter WebServices API
Home-page: https://github.com/HEPData/hepdata-converter-ws-client
Author: HEPData Team
Author-email: info@hepdata.net
License: GPL
Download-URL: https://github.com/HEPData/hepdata-converter-ws-client/tarball/0.2.2
Platform: UNKNOWN
Requires-Python: ~=3.6
Requires-Dist: future (>=0.18.2)
Requires-Dist: requests (>=2.23.0)
Provides-Extra: tests
Requires-Dist: pyyaml (>=5.3) ; extra == 'tests'
